{"assets/icons/12617110861599778126.svg":["assets/icons/12617110861599778126.svg"],"assets/icons/14611243551599778133.svg":["assets/icons/14611243551599778133.svg"],"assets/icons/17485654861584409101.svg":["assets/icons/17485654861584409101.svg"],"assets/icons/20479336791548336236.svg":["assets/icons/20479336791548336236.svg"],"assets/icons/7242212131579605499.svg":["assets/icons/7242212131579605499.svg"],"assets/icons/855041791547464161.svg":["assets/icons/855041791547464161.svg"],"assets/icons/Documents.svg":["assets/icons/Documents.svg"],"assets/icons/Figma_file.svg":["assets/icons/Figma_file.svg"],"assets/icons/Search.svg":["assets/icons/Search.svg"],"assets/icons/convid.svg":["assets/icons/convid.svg"],"assets/icons/convid2.svg":["assets/icons/convid2.svg"],"assets/icons/covid3.svg":["assets/icons/covid3.svg"],"assets/icons/doc_file.svg":["assets/icons/doc_file.svg"],"assets/icons/drop_box.svg":["assets/icons/drop_box.svg"],"assets/icons/excle_file.svg":["assets/icons/excle_file.svg"],"assets/icons/folder.svg":["assets/icons/folder.svg"],"assets/icons/google_drive.svg":["assets/icons/google_drive.svg"],"assets/icons/logo.svg":["assets/icons/logo.svg"],"assets/icons/media.svg":["assets/icons/media.svg"],"assets/icons/media_file.svg":["assets/icons/media_file.svg"],"assets/icons/menu_dashbord.svg":["assets/icons/menu_dashbord.svg"],"assets/icons/menu_doc.svg":["assets/icons/menu_doc.svg"],"assets/icons/menu_notification.svg":["assets/icons/menu_notification.svg"],"assets/icons/menu_profile.svg":["assets/icons/menu_profile.svg"],"assets/icons/menu_setting.svg":["assets/icons/menu_setting.svg"],"assets/icons/menu_store.svg":["assets/icons/menu_store.svg"],"assets/icons/menu_task.svg":["assets/icons/menu_task.svg"],"assets/icons/menu_tran.svg":["assets/icons/menu_tran.svg"],"assets/icons/mosquito.svg":["assets/icons/mosquito.svg"],"assets/icons/mosquito2.svg":["assets/icons/mosquito2.svg"],"assets/icons/one_drive.svg":["assets/icons/one_drive.svg"],"assets/icons/patient.svg":["assets/icons/patient.svg"],"assets/icons/patient2.svg":["assets/icons/patient2.svg"],"assets/icons/pdf_file.svg":["assets/icons/pdf_file.svg"],"assets/icons/register.svg":["assets/icons/register.svg"],"assets/icons/register2.svg":["assets/icons/register2.svg"],"assets/icons/sound_file.svg":["assets/icons/sound_file.svg"],"assets/icons/unknown.svg":["assets/icons/unknown.svg"],"assets/icons/user.svg":["assets/icons/user.svg"],"assets/icons/xd_file.svg":["assets/icons/xd_file.svg"],"assets/images/Malawi-Coat_of_arms_of_arms.png":["assets/images/Malawi-Coat_of_arms_of_arms.png"],"assets/images/PEPFAR2.jpeg":["assets/images/PEPFAR2.jpeg"],"assets/images/profile_pic.png":["assets/images/profile_pic.png"],"packages/cupertino_icons/assets/CupertinoIcons.ttf":["packages/cupertino_icons/assets/CupertinoIcons.ttf"]}